design.sv
// Code your design here

module seq_detect(output y, input in, clk, rst);  //searching for "0110"
  reg y;
  reg [0:1] ps, ns ;  //ps- present state ns- next state
  parameter S0=2'b00, S1=2'b01, S2=2'b10, S3=2'b11;  //parameters for state;
  
  always@(ps, in, rst) begin     //block for assignment of states based upon input;
    if(rst) begin
      ps = S0;
    end else begin
      case(ps)
        S0: begin			//S0: seen "nothing" state;
          ns = in?S0:S1;
        end
        S1: begin			//S1: seen "0" state;
          ns = in?S2:S1;
        end
        S2: begin			//S2: seen "01" state;
          ns = in?S3:S1;
        end
        S3: begin			//S3: seen "011" state;
          ns = in?S0:S1;
        end
        default: begin
          ns = S0;
        end
      endcase
    end
  end
 
  
  always@(posedge clk, posedge rst) begin     //assignment of states and output in sync with clock;
    ps <= ns;
    y <= ({ps,~in}==3'b111)?1:0;
  end
endmodule

testbench.sv
// Code your testbench here
// or browse Examples

module t_seq_detect;
  wire y;
  reg in, clk, rst;
  
  seq_detect M_UUT(y, in, clk, rst);
  
  always
    #5 clk = ~clk;
  
  initial
    begin
      $dumpfile("waveSeq.vcd");
      $dumpvars(0, y, in, clk, rst);
      $monitor($time," clk= %b , rst=%b, in= %b , output= %b ", clk, rst, in, y);
      clk=1'b0; in=1'b0; rst=1'b1;
      #2 rst=1'b0;
      #10 in=1'b1;
      #20 in=1'b0;
      #10 in=1'b1;
      #30 in=1'b0;
      #10 in=1'b1;
      #10 in=1'b0;
      #10 in=1'b1;
      #20 in=1'b0;
      #10 in=1'b1;
      #10 rst=1'b1;
      #10 rst=1'b0; in=1'b0;
      #10 in=1'b1;
      #20 in=1'b0;
      #60 $finish;
    end
endmodule

waveSeq.vcd
$date
	Wed May 13 17:28:04 2020
$end
$version
	Icarus Verilog
$end
$timescale
	1s
$end
$scope module t_seq_detect $end
$var wire 1 ! y $end
$upscope $end
$scope module t_seq_detect $end
$var reg 1 " in $end
$upscope $end
$scope module t_seq_detect $end
$var reg 1 # clk $end
$upscope $end
$scope module t_seq_detect $end
$var reg 1 $ rst $end
$upscope $end
$enddefinitions $end
#0
$dumpvars
1$
0#
0"
0!
$end
#2
0$
#5
1#
#10
0#
#12
1"
#15
1#
#20
0#
#25
1#
#30
0#
#32
0"
#35
1!
1#
#40
0#
#42
1"
#45
0!
1#
#50
0#
#55
1#
#60
0#
#65
1#
#70
0#
#72
0"
#75
1#
#80
0#
#82
1"
#85
1#
#90
0#
#92
0"
#95
1#
#100
0#
#102
1"
#105
1#
#110
0#
#115
1#
#120
0#
#122
0"
#125
1!
1#
#130
0#
#132
1"
#135
0!
1#
#140
0#
#142
1$
#145
1#
#150
0#
#152
0"
0$
#155
1#
#160
0#
#162
1"
#165
1#
#170
0#
#175
1#
#180
0#
#182
0"
#185
1!
1#
#190
0#
#195
0!
1#
